Mux_2x1.v
module Mux_2x1(y,I,s);
input [1:0]I;
input s;
output y;
wire [2:0]w;
not g1 (w[0],s);
and g2 (w[1],w[0],I[0]);
and g3 (w[2],s,I[1]);
or g4 (y,w[1],w[2]);
endmodule

Mux_4x1.v
module Mux_4x1(y,I,s);
output y ;
input [3:0] I;
input [1:0] s;
wire [1:0]w;
wire [3:0]p;
not g1(w[1],s[1]);
not g2(w[0],s[0]);
and g3(p[0],w[1],w[0],I[0]);
and g4(p[1],w[1],s[0],I[1]);
and g5(p[2],s[1],w[0],I[2]);
and g6(p[3],s[1],s[0],I[3]);
or g7(y,p[0],p[1],p[2],p[3]);
endmodule

Mux_8x1.v
module Mux_8x1(y,I,s);
output y;
input [7:0]I;
input [2:0]s;
wire [1:0]w;
//instaint mux_4x1 and mux_2x1
Mux_4x1 m1(.y(w[0]), .I(I[3:0]), .s(s[1:0]));
Mux_4x1 m2(.y(w[1]), .I(I[7:4]), .s(s[1:0]));
Mux_2x1 m3(.y(y), .I(w[1:0]), .s(s[2]));
endmodule

Mux_8x1_tv.v
module tb;
reg [7:0]I;
reg [2:0]s;
wire y;
Mux_8x1 dut (.y(y), .I(I), .s(s));
initial begin
    $dumpfile("wave.vcd");
    $dumpvars(0,tb);
I = 8'b10101010;
s=3'b000;
#10 s=3'b001;
#10 s=3'b010;
#10 s=3'b011;
#10 s=3'b100;
#10 s=3'b101;
#10 s=3'b110;
#10 s=3'b111;
end
initial begin
    $monitor("Time=%0t y=%b I=%b s=%b", $time, y, I,s);
end
endmodule

wave.vcd
$date
	Mon Jun 22 00:11:24 2026
$end
$version
	Icarus Verilog
$end
$timescale
	1s
$end
$scope module tb $end
$var wire 1 ! y $end
$var reg 8 " I [7:0] $end
$var reg 3 # s [2:0] $end
$scope module dut $end
$var wire 8 $ I [7:0] $end
$var wire 3 % s [2:0] $end
$var wire 1 ! y $end
$var wire 2 & w [1:0] $end
$scope module m1 $end
$var wire 4 ' I [3:0] $end
$var wire 2 ( s [1:0] $end
$var wire 1 ) y $end
$var wire 2 * w [1:0] $end
$var wire 4 + p [3:0] $end
$upscope $end
$scope module m2 $end
$var wire 4 , I [3:0] $end
$var wire 2 - s [1:0] $end
$var wire 1 . y $end
$var wire 2 / w [1:0] $end
$var wire 4 0 p [3:0] $end
$upscope $end
$scope module m3 $end
$var wire 2 1 I [1:0] $end
$var wire 1 2 s $end
$var wire 1 ! y $end
$var wire 3 3 w [2:0] $end
$upscope $end
$upscope $end
$upscope $end
$enddefinitions $end
$comment Show the parameter values. $end
$dumpall
$end
#0
$dumpvars
b1 3
02
b0 1
b0 0
b11 /
0.
b0 -
b1010 ,
b0 +
b11 *
0)
b0 (
b1010 '
b0 &
b0 %
b10101010 $
b0 #
b10101010 "
0!
$end
#10
1!
b11 3
1)
b11 &
b11 1
1.
b10 *
b10 +
b10 /
b10 0
b1 (
b1 -
b1 #
b1 %
#20
0!
b1 3
0)
b0 &
b0 1
0.
b1 *
b0 +
b1 /
b0 0
b10 (
b10 -
b10 #
b10 %
#30
1!
b11 3
1)
b11 &
b11 1
1.
b0 *
b1000 +
b0 /
b1000 0
b11 (
b11 -
b11 #
b11 %
#40
0!
0)
b0 &
b0 1
0.
b11 *
b0 +
b11 /
b0 0
b0 3
b0 (
b0 -
12
b100 #
b100 %
#50
1!
b100 3
1)
b11 &
b11 1
1.
b10 *
b10 +
b10 /
b10 0
b1 (
b1 -
b101 #
b101 %
#60
0!
b0 3
0)
b0 &
b0 1
0.
b1 *
b0 +
b1 /
b0 0
b10 (
b10 -
b110 #
b110 %
#70
1!
b100 3
1)
b11 &
b11 1
1.
b0 *
b1000 +
b0 /
b1000 0
b11 (
b11 -
b111 #
b111 %
